sim_toolkit/__init__.py
sim_toolkit/_deps.py
sim_toolkit/_utils.py
sim_toolkit/api.py
sim_toolkit/legacy.py
sim_toolkit/Images/Metrics.png
sim_toolkit/Images/Metrics.png.license
sim_toolkit/Images/logo.png
sim_toolkit/Images/logo.png.license
sim_toolkit/datasets/README.md
sim_toolkit/datasets/base.py
sim_toolkit/datasets/dcm.py
sim_toolkit/datasets/init.py
sim_toolkit/datasets/jpeg.py
sim_toolkit/datasets/metrics_2D_TIFF_MU.py
sim_toolkit/datasets/metrics_3D_TIFF_MU.py
sim_toolkit/datasets/nifti.py
sim_toolkit/datasets/nifti_prova.py
sim_toolkit/datasets/png.py
sim_toolkit/datasets/tiff.py
sim_toolkit/dnnlib/__init__.py
sim_toolkit/dnnlib/util.py
sim_toolkit/metrics/__init__.py
sim_toolkit/metrics/create_report.py
sim_toolkit/metrics/frechet_inception_distance.py
sim_toolkit/metrics/inception_score.py
sim_toolkit/metrics/kernel_inception_distance.py
sim_toolkit/metrics/knn_analysis.py
sim_toolkit/metrics/metric_main.py
sim_toolkit/metrics/metric_utils.py
sim_toolkit/metrics/pr_authen.py
sim_toolkit/metrics/pr_dc.py
sim_toolkit/representations/OneClass.py
sim_toolkit/representations/__init__.py
sim_toolkit/representations/networks.py
sim_toolkit/representations/resnet3d.py
sim_toolkit/representations/ts_embedding/__init__.py
sim_toolkit/representations/ts_embedding/seq2seq_autoencoder.py
sim_toolkit/representations/ts_embedding/training.py
sim_toolkit/representations/ts_embedding/utils.py
sim_toolkit/torch_utils/__init__.py
sim_toolkit/torch_utils/custom_ops.py
sim_toolkit/torch_utils/misc.py
sim_toolkit/torch_utils/persistence.py
sim_toolkit/torch_utils/training_stats.py
sim_toolkit/torch_utils/ops/__init__.py
sim_toolkit/torch_utils/ops/bias_act.cpp
sim_toolkit/torch_utils/ops/bias_act.cu
sim_toolkit/torch_utils/ops/bias_act.h
sim_toolkit/torch_utils/ops/bias_act.py
sim_toolkit/torch_utils/ops/conv2d_gradfix.py
sim_toolkit/torch_utils/ops/conv2d_resample.py
sim_toolkit/torch_utils/ops/fma.py
sim_toolkit/torch_utils/ops/grid_sample_gradfix.py
sim_toolkit-4.1.1.dist-info/METADATA
sim_toolkit-4.1.1.dist-info/WHEEL
sim_toolkit-4.1.1.dist-info/RECORD
