Metadata-Version: 2.4
Name: sim_toolkit
Version: 4.1.1
Summary: Synthetic Images Metrics Toolkit (SIM Toolkit)
Author-email: Matteo Lai <matteo.lai3@unibo.it>
License: NPOSL-3.0
Keywords: generative,images,medical-imaging,metrics,synthetic images,validation
Classifier: Intended Audience :: Science/Research
Classifier: Operating System :: OS Independent
Classifier: Programming Language :: Python :: 3
Classifier: Programming Language :: Python :: 3 :: Only
Classifier: Topic :: Scientific/Engineering :: Image Processing
Requires-Python: <3.13,>=3.10
Requires-Dist: click>=8.1
Requires-Dist: imageio-ffmpeg>=0.4.3
Requires-Dist: matplotlib<3.8,>=3.5
Requires-Dist: numpy<2,>=1.23; python_version < '3.12'
Requires-Dist: numpy<2,>=1.26; python_version >= '3.12'
Requires-Dist: pillow>=9.0
Requires-Dist: psutil>=5.7
Requires-Dist: pyspng>=0.1.1
Requires-Dist: reportlab>=4.0
Requires-Dist: requests>=2.24
Requires-Dist: scikit-learn<1.3,>=1.0; python_version < '3.12'
Requires-Dist: scikit-learn<1.6,>=1.3; python_version >= '3.12'
Requires-Dist: scipy>=1.15
Requires-Dist: seaborn>=0.13
Requires-Dist: tqdm>=4.64
Provides-Extra: csv
Requires-Dist: pandas>=1.5; extra == 'csv'
Provides-Extra: dev
Requires-Dist: build>=1.0; extra == 'dev'
Requires-Dist: mkdocs-material>=9.5; extra == 'dev'
Requires-Dist: mypy>=1.8; extra == 'dev'
Requires-Dist: pytest-cov>=4.1; extra == 'dev'
Requires-Dist: pytest>=7.0; extra == 'dev'
Requires-Dist: ruff>=0.5; extra == 'dev'
Requires-Dist: twine>=5.0; extra == 'dev'
Provides-Extra: dicom
Requires-Dist: pydicom; extra == 'dicom'
Provides-Extra: nifti
Requires-Dist: nibabel>=5.0; extra == 'nifti'
Provides-Extra: opencv
Requires-Dist: opencv-python>=4.8; extra == 'opencv'
Provides-Extra: tf
Requires-Dist: keras<2.13,>=2.12; (python_version < '3.12') and extra == 'tf'
Requires-Dist: protobuf<4.0,>=3.20; extra == 'tf'
Requires-Dist: tensorflow-macos<2.13,>=2.12; (python_version < '3.12' and sys_platform == 'darwin' and platform_machine == 'arm64') and extra == 'tf'
Requires-Dist: tensorflow<2.13,>=2.12; (python_version < '3.12' and platform_machine == 'AMD64' and sys_platform == 'win32') and extra == 'tf'
Requires-Dist: tensorflow<2.13,>=2.12; (python_version < '3.12' and platform_machine == 'x86_64' and sys_platform != 'darwin') and extra == 'tf'
Requires-Dist: typing-extensions>=4.12; extra == 'tf'
Provides-Extra: tiff
Requires-Dist: imagecodecs>=2023.1.23; (platform_system != 'Windows') and extra == 'tiff'
Requires-Dist: tifffile>=2023.2.3; extra == 'tiff'
Provides-Extra: torch
Requires-Dist: torch>=2.1; extra == 'torch'
Requires-Dist: torchvision>=0.16; extra == 'torch'
